{
  "_class": "shapePath",
  "booleanOperation": -1,
  "clippingMaskMode": 0,
  "do_objectID": "D64F2B03-25A5-4802-B845-439B10F627C6",
  "edited": true,
  "exportOptions": {
    "_class": "exportOptions",
    "exportFormats": [
    ],
    "includedLayerIds": [
    ],
    "layerOptions": 0,
    "shouldTrim": false
  },
  "frame": {
    "_class": "rect",
    "constrainProportions": false,
    "height": 38.49999999999977,
    "width": 1,
    "x": 224.5,
    "y": 110.5000000000002
  },
  "hasClippingMask": false,
  "isClosed": false,
  "isFixedToViewport": false,
  "isFlippedHorizontal": false,
  "isFlippedVertical": false,
  "isLocked": false,
  "isVisible": true,
  "layerListExpandedType": 0,
  "name": "Line 4 Copy",
  "nameIsFixed": false,
  "pointRadiusBehaviour": 1,
  "points": [
    {
      "_class": "curvePoint",
      "cornerRadius": 0,
      "curveFrom": "{1.4999999999999998, 0.99999999999999978}",
      "curveMode": 1,
      "curveTo": "{1.4999999999999998, 0.99999999999999978}",
      "hasCurveFrom": false,
      "hasCurveTo": false,
      "point": "{0.5, 1}"
    },
    {
      "_class": "curvePoint",
      "cornerRadius": 0,
      "curveFrom": "{1.5, 1.0129870129870187}",
      "curveMode": 1,
      "curveTo": "{1.5, 1.0129870129870187}",
      "hasCurveFrom": false,
      "hasCurveTo": false,
      "point": "{0.5, 0}"
    }
  ],
  "resizingConstraint": 63,
  "resizingType": 0,
  "rotation": 0,
  "shouldBreakMaskChain": false,
  "style": {
    "_class": "style",
    "borderOptions": {
      "_class": "borderOptions",
      "dashPattern": [
      ],
      "isEnabled": false,
      "lineCapStyle": 2,
      "lineJoinStyle": 0
    },
    "borders": [
      {
        "_class": "border",
        "color": {
          "_class": "color",
          "alpha": 1,
          "blue": 0.9372549019607843,
          "green": 0.9294117647058824,
          "red": 0.9098039215686274
        },
        "fillType": 0,
        "isEnabled": true,
        "position": 0,
        "thickness": 1
      }
    ],
    "endMarkerType": 0,
    "fills": [
      {
        "_class": "fill",
        "color": {
          "_class": "color",
          "alpha": 1,
          "blue": 0.6577115221088435,
          "green": 0.6577115221088435,
          "red": 0.6577115221088435
        },
        "fillType": 0,
        "isEnabled": false,
        "noiseIndex": 0,
        "noiseIntensity": 0,
        "patternFillType": 0,
        "patternTileScale": 1
      }
    ],
    "miterLimit": 10,
    "startMarkerType": 0,
    "windingRule": 0
  }
}