{
  "_class": "shapePath",
  "booleanOperation": -1,
  "clippingMaskMode": 0,
  "do_objectID": "D3A0AF4E-FF36-4EFC-98CD-10086BFAA5AA",
  "edited": true,
  "exportOptions": {
    "_class": "exportOptions",
    "exportFormats": [
    ],
    "includedLayerIds": [
    ],
    "layerOptions": 0,
    "shouldTrim": false
  },
  "frame": {
    "_class": "rect",
    "constrainProportions": false,
    "height": 5.555555555555554,
    "width": 20,
    "x": 0,
    "y": 0
  },
  "hasClippingMask": false,
  "isClosed": true,
  "isFixedToViewport": false,
  "isFlippedHorizontal": false,
  "isFlippedVertical": false,
  "isLocked": false,
  "isVisible": true,
  "layerListExpandedType": 0,
  "name": "Path",
  "nameIsFixed": false,
  "pointRadiusBehaviour": 1,
  "points": [
    {
      "_class": "curvePoint",
      "cornerRadius": 0,
      "curveFrom": "{0.97916666666666663, 0.40000000000000002}",
      "curveMode": 4,
      "curveTo": "{0.99062500000000009, 0.40000000000000002}",
      "hasCurveFrom": false,
      "hasCurveTo": true,
      "point": "{0.97916666666666663, 0.40000000000000002}"
    },
    {
      "_class": "curvePoint",
      "cornerRadius": 0,
      "curveFrom": "{0.27777777777777779, 0.40000000000000002}",
      "curveMode": 1,
      "curveTo": "{0.27777777777777779, 0.40000000000000002}",
      "hasCurveFrom": false,
      "hasCurveTo": false,
      "point": "{0.27777777777777779, 0.40000000000000002}"
    },
    {
      "_class": "curvePoint",
      "cornerRadius": 0,
      "curveFrom": "{0.27777777777777779, 0.067499999999999977}",
      "curveMode": 4,
      "curveTo": "{0.27777777777777779, 0.14999999999999999}",
      "hasCurveFrom": true,
      "hasCurveTo": false,
      "point": "{0.27777777777777779, 0.14999999999999999}"
    },
    {
      "_class": "curvePoint",
      "cornerRadius": 0,
      "curveFrom": "{0.2361111111111111, 0}",
      "curveMode": 4,
      "curveTo": "{0.25902777777777775, 0}",
      "hasCurveFrom": false,
      "hasCurveTo": true,
      "point": "{0.2361111111111111, 0}"
    },
    {
      "_class": "curvePoint",
      "cornerRadius": 0,
      "curveFrom": "{0.12986111111111109, 0}",
      "curveMode": 4,
      "curveTo": "{0.15277777777777779, 0}",
      "hasCurveFrom": true,
      "hasCurveTo": false,
      "point": "{0.15277777777777779, 0}"
    },
    {
      "_class": "curvePoint",
      "cornerRadius": 0,
      "curveFrom": "{0.1111111111111111, 0.14999999999999999}",
      "curveMode": 4,
      "curveTo": "{0.1111111111111111, 0.067499999999999977}",
      "hasCurveFrom": false,
      "hasCurveTo": true,
      "point": "{0.1111111111111111, 0.14999999999999999}"
    },
    {
      "_class": "curvePoint",
      "cornerRadius": 0,
      "curveFrom": "{0.1111111111111111, 0.40000000000000002}",
      "curveMode": 1,
      "curveTo": "{0.1111111111111111, 0.40000000000000002}",
      "hasCurveFrom": false,
      "hasCurveTo": false,
      "point": "{0.1111111111111111, 0.40000000000000002}"
    },
    {
      "_class": "curvePoint",
      "cornerRadius": 0,
      "curveFrom": "{0.0093750000000000014, 0.40000000000000002}",
      "curveMode": 4,
      "curveTo": "{0.020833333333333332, 0.40000000000000002}",
      "hasCurveFrom": true,
      "hasCurveTo": false,
      "point": "{0.020833333333333332, 0.40000000000000002}"
    },
    {
      "_class": "curvePoint",
      "cornerRadius": 0,
      "curveFrom": "{0, 0.47499999999999998}",
      "curveMode": 4,
      "curveTo": "{0, 0.43375000000000002}",
      "hasCurveFrom": false,
      "hasCurveTo": true,
      "point": "{0, 0.47499999999999998}"
    },
    {
      "_class": "curvePoint",
      "cornerRadius": 0,
      "curveFrom": "{0, 0.56624999999999992}",
      "curveMode": 4,
      "curveTo": "{0, 0.52500000000000002}",
      "hasCurveFrom": true,
      "hasCurveTo": false,
      "point": "{0, 0.52500000000000002}"
    },
    {
      "_class": "curvePoint",
      "cornerRadius": 0,
      "curveFrom": "{0.020833333333333332, 0.59999999999999998}",
      "curveMode": 4,
      "curveTo": "{0.0093750000000000014, 0.59999999999999998}",
      "hasCurveFrom": false,
      "hasCurveTo": true,
      "point": "{0.020833333333333332, 0.59999999999999998}"
    },
    {
      "_class": "curvePoint",
      "cornerRadius": 0,
      "curveFrom": "{0.1111111111111111, 0.59999999999999998}",
      "curveMode": 1,
      "curveTo": "{0.1111111111111111, 0.59999999999999998}",
      "hasCurveFrom": false,
      "hasCurveTo": false,
      "point": "{0.1111111111111111, 0.59999999999999998}"
    },
    {
      "_class": "curvePoint",
      "cornerRadius": 0,
      "curveFrom": "{0.1111111111111111, 0.93249999999999988}",
      "curveMode": 4,
      "curveTo": "{0.1111111111111111, 0.84999999999999998}",
      "hasCurveFrom": true,
      "hasCurveTo": false,
      "point": "{0.1111111111111111, 0.84999999999999998}"
    },
    {
      "_class": "curvePoint",
      "cornerRadius": 0,
      "curveFrom": "{0.15277777777777779, 1}",
      "curveMode": 4,
      "curveTo": "{0.12986111111111109, 1}",
      "hasCurveFrom": false,
      "hasCurveTo": true,
      "point": "{0.15277777777777779, 1}"
    },
    {
      "_class": "curvePoint",
      "cornerRadius": 0,
      "curveFrom": "{0.25902777777777775, 1}",
      "curveMode": 4,
      "curveTo": "{0.2361111111111111, 1}",
      "hasCurveFrom": true,
      "hasCurveTo": false,
      "point": "{0.2361111111111111, 1}"
    },
    {
      "_class": "curvePoint",
      "cornerRadius": 0,
      "curveFrom": "{0.27777777777777779, 0.84999999999999998}",
      "curveMode": 4,
      "curveTo": "{0.27777777777777779, 0.93249999999999988}",
      "hasCurveFrom": false,
      "hasCurveTo": true,
      "point": "{0.27777777777777779, 0.84999999999999998}"
    },
    {
      "_class": "curvePoint",
      "cornerRadius": 0,
      "curveFrom": "{0.27777777777777779, 0.59999999999999998}",
      "curveMode": 1,
      "curveTo": "{0.27777777777777779, 0.59999999999999998}",
      "hasCurveFrom": false,
      "hasCurveTo": false,
      "point": "{0.27777777777777779, 0.59999999999999998}"
    },
    {
      "_class": "curvePoint",
      "cornerRadius": 0,
      "curveFrom": "{0.99062500000000009, 0.59999999999999998}",
      "curveMode": 4,
      "curveTo": "{0.97916666666666663, 0.59999999999999998}",
      "hasCurveFrom": true,
      "hasCurveTo": false,
      "point": "{0.97916666666666663, 0.59999999999999998}"
    },
    {
      "_class": "curvePoint",
      "cornerRadius": 0,
      "curveFrom": "{1, 0.52500000000000002}",
      "curveMode": 4,
      "curveTo": "{1, 0.56624999999999992}",
      "hasCurveFrom": false,
      "hasCurveTo": true,
      "point": "{1, 0.52500000000000002}"
    },
    {
      "_class": "curvePoint",
      "cornerRadius": 0,
      "curveFrom": "{1, 0.43375000000000002}",
      "curveMode": 4,
      "curveTo": "{1, 0.47499999999999998}",
      "hasCurveFrom": true,
      "hasCurveTo": false,
      "point": "{1, 0.47499999999999998}"
    }
  ],
  "resizingConstraint": 63,
  "resizingType": 0,
  "rotation": 0,
  "shouldBreakMaskChain": false,
  "style": {
    "_class": "style",
    "endMarkerType": 0,
    "fills": [
      {
        "_class": "fill",
        "color": {
          "_class": "color",
          "alpha": 1,
          "blue": 0,
          "green": 0,
          "red": 0
        },
        "fillType": 0,
        "isEnabled": true,
        "noiseIndex": 0,
        "noiseIntensity": 0,
        "patternFillType": 1,
        "patternTileScale": 1
      }
    ],
    "miterLimit": 10,
    "startMarkerType": 0,
    "windingRule": 0
  }
}