{
  "_class": "symbolInstance",
  "booleanOperation": 0,
  "clippingMaskMode": 0,
  "do_objectID": "DB193CD7-F0A3-4101-8187-A8E2AF2213B2",
  "exportOptions": {
    "_class": "exportOptions",
    "do_objectID": "722C2419-FD04-499F-B30C-85D53A3B51CF",
    "exportFormats": [
    ],
    "includedLayerIds": [
    ],
    "layerOptions": 0,
    "shouldTrim": false
  },
  "frame": {
    "_class": "rect",
    "constrainProportions": false,
    "do_objectID": "75371D6A-8933-43AD-A58C-45842960260B",
    "height": 15,
    "width": 62,
    "x": 21,
    "y": 590
  },
  "hasClippingMask": false,
  "horizontalSpacing": 0,
  "isFixedToViewport": false,
  "isFlippedHorizontal": false,
  "isFlippedVertical": false,
  "isLocked": false,
  "isVisible": true,
  "layerListExpandedType": 0,
  "name": "text",
  "nameIsFixed": false,
  "overrideValues": [
    {
      "_class": "overrideValue",
      "overrideName": "B71173B1-2A80-4F48-8688-659756DB9C1B_stringValue",
      "value": "Created"
    }
  ],
  "resizingConstraint": 63,
  "resizingType": 0,
  "rotation": 0,
  "scale": 1,
  "shouldBreakMaskChain": false,
  "style": {
    "_class": "style",
    "do_objectID": "C40510CD-C28D-4735-B547-3A817D69CF6A",
    "endMarkerType": 0,
    "miterLimit": 10,
    "startMarkerType": 0,
    "windingRule": 1
  },
  "symbolID": "B1B63AE8-36D8-4CA2-8B16-258A8FCFD6B6",
  "verticalSpacing": 0
}