{
  "_class": "symbolInstance",
  "booleanOperation": 0,
  "clippingMaskMode": 0,
  "do_objectID": "318C4FE1-9ED9-4C9F-900F-EAD412E4BEC7",
  "exportOptions": {
    "_class": "exportOptions",
    "do_objectID": "955C2A78-C4B0-4D37-83FD-B29569B3BBA6",
    "exportFormats": [
    ],
    "includedLayerIds": [
    ],
    "layerOptions": 0,
    "shouldTrim": false
  },
  "frame": {
    "_class": "rect",
    "constrainProportions": false,
    "do_objectID": "4994AA60-1D38-400A-9CF0-C32E99099484",
    "height": 220,
    "width": 1140,
    "x": 128,
    "y": 110
  },
  "hasClippingMask": false,
  "horizontalSpacing": 0,
  "isFixedToViewport": false,
  "isFlippedHorizontal": false,
  "isFlippedVertical": false,
  "isLocked": true,
  "isVisible": true,
  "layerListExpandedType": 0,
  "name": "Tile",
  "nameIsFixed": false,
  "overrideValues": [
  ],
  "resizingConstraint": 63,
  "resizingType": 0,
  "rotation": 0,
  "scale": 1,
  "shouldBreakMaskChain": false,
  "style": {
    "_class": "style",
    "do_objectID": "CF7DD362-DAFD-4B8A-8C0C-1966F5C87658",
    "endMarkerType": 0,
    "miterLimit": 10,
    "startMarkerType": 0,
    "windingRule": 1
  },
  "symbolID": "9DF1C81D-521C-479A-8E22-13396B542990",
  "verticalSpacing": 0
}